pyResourceHandler.py
pyresourcehandler-1.0.4.dist-info/LICENSE
pyresourcehandler-1.0.4.dist-info/WHEEL
pyresourcehandler-1.0.4.dist-info/METADATA
pyresourcehandler-1.0.4.dist-info/RECORD
