Metadata-Version: 2.1
Name: pyresourcehandler
Version: 1.0.4
Summary: 
Author: icySnippets
Author-email: admin@icysnippets.com
Requires-Python: >=3.9
Classifier: Programming Language :: Python :: 3
Classifier: Programming Language :: Python :: 3.9
Classifier: Programming Language :: Python :: 3.10
